LICENSE
MANIFEST.in
README.md
requirements.txt
setup.py
PygameMenus/__init__.py
PygameMenus/button.py
PygameMenus/buttonblock.py
PygameMenus/buttoncolors.py
PygameMenus/examples.py
PygameMenus/menu.py
PygameMenus/title.py
PygameMenus/utils.py
PygameMenus.egg-info/PKG-INFO
PygameMenus.egg-info/SOURCES.txt
PygameMenus.egg-info/dependency_links.txt
PygameMenus.egg-info/requires.txt
PygameMenus.egg-info/top_level.txt